Workbook

Sheet Contents
A1: SHOE STORE FEASIBILITY & FINANCIAL MODEL
A2: El Warraq, Giza, Egypt — Prepared for internal planning, investor & bank presentation
A4: # | B4: Section | C4: Description
A5: 1 | B5: Business Info | C5: Store profile, concept, target market
A6: 2 | B6: Startup Costs | C6: One-time pre-opening investment budget
A7: 3 | B7: Monthly Expenses | C7: Recurring monthly operating costs
A8: 4 | B8: Inventory Plan | C8: Initial stock purchase plan by supplier/model
A9: 5 | B9: Suppliers | C9: Supplier directory & ratings
A10: 6 | B10: Sales Forecast | C10: Conservative / Expected / Optimistic projections
A11: 7 | B11: Break-Even | C11: Break-even units, revenue and timing
A12: 8 | B12: Cash Flow | C12: 12-month monthly cash flow projection
A13: 9 | B13: P&L | C13: Monthly & yearly profit and loss statement
A14: 10 | B14: Inventory Tracker | C14: Live stock levels & movement classification
A15: 11 | B15: Product Dashboard | C15: Top/worst sellers and margin leaders + chart
A16: 12 | B16: Expense Tracker | C16: Log of actual expenses with category summary
... A24: 20 | B24: Final Summary | C24: Investor/bank-ready feasibility snapshot
A27: How to use this workbook: 1) Fill in Business Info, Startup Costs, Monthly Expenses, Inventory Plan and Sales Forecast (yellow cells). 2) Break-Even, Cash Flow, P&L, KPI Dashboard and Final Summary calculate automatically. 3) Use Suppliers, Market Research, Risk Analysis, Marketing Plan, SWOT and Action Plan as planning worksheets. 4) Use Inventory/Expense/Sales Trackers once the store is operating, to keep the model live and accurate. Yellow cells = editable inputs. Blue/white cells = automatic formulas (protected).

Sheet Business Info
A1: SHOE STORE FEASIBILITY MODEL
A2: Business Information | El Warraq, Giza, Egypt
A4: INPUT FIELD | B4: VALUE
A5: Store Name | B5: Enter store name
A6: Store Location | B6: El Warraq, Giza, Egypt
A7: Store Size (sqm) | B7: 60
A8: Store Frontage (m) | B8: 6
A9: Opening Date | B9: 46023
A10: Business Owner | B10: Enter owner name
A11: Store Concept | B11: Value-for-money family footwear store
A12: Target Market | B12: Middle-income families, El Warraq & Greater Giza
A14: NOTES
A15: Add any relevant notes about the business concept, positioning, competitive advantage, etc.
A21: Legend: Yellow cells = editable inputs. All other sheets pull data automatically from here where relevant.

Sheet Startup Costs
A1: STARTUP COSTS
A2: One-time pre-opening investment budget (EGP)
A4: # | B4: Cost Item | C4: Amount (EGP) | D4: Notes
A5: 1 | B5: Security Deposit | C5: 0
A6: 2 | B6: Rent (advance) | C6: 0
A7: 3 | B7: Renovation | C7: 0
A8: 4 | B8: Painting | C8: 0
A9: 5 | B9: Flooring | C9: 0
A10: 6 | B10: Shelves | C10: 0
A11: 7 | B11: Shoe Display Racks | C11: 0
A12: 8 | B12: Mirrors | C12: 0
A13: 9 | B13: Signboard | C13: 0
A14: 10 | B14: Lighting | C14: 0
A15: 11 | B15: Cash Counter | C15: 0
A16: 12 | B16: POS System | C16: 0
... A33: 29 | B33: Miscellaneous / Contingency | C33: 0
B35: TOTAL STARTUP COST | C35: =SUM(C5:C33)
A37: Legend: Yellow cells are editable inputs. Enter your actual quotes/estimates in EGP; the total updates automatically. Add rows above the total row as needed for future expansion.

Sheet Monthly Expenses
A1: MONTHLY OPERATING EXPENSES
A2: Recurring fixed & variable monthly costs (EGP)
A4: # | B4: Expense Category | C4: Amount (EGP) / Month | D4: Notes
A5: 1 | B5: Rent | C5: 0
A6: 2 | B6: Employee Salaries | C6: 0
A7: 3 | B7: Electricity | C7: 0
A8: 4 | B8: Water | C8: 0
A9: 5 | B9: Internet | C9: 0
A10: 6 | B10: Cleaning | C10: 0
A11: 7 | B11: Packaging Materials | C11: 0
A12: 8 | B12: Transportation | C12: 0
A13: 9 | B13: Maintenance | C13: 0
A14: 10 | B14: Taxes | C14: 0
A15: 11 | B15: Marketing | C15: 0
A16: 12 | B16: Unexpected Expenses | C16: 0
A17: 13 | B17: Other Expenses | C17: 0
B19: TOTAL MONTHLY EXPENSES | C19: =SUM(C5:C17)
A21: Legend: Yellow cells are editable inputs. This monthly total feeds the Cash Flow, P&L and Break-Even sheets automatically.

Sheet Inventory Plan
A1: INVENTORY PURCHASE PLAN
A2: Initial stock order plan across suppliers
A4: Supplier | B4: Factory | C4: Category | D4: Gender | E4: Product Type | F4: Model Name | G4: Color | H4: Size Range | I4: Cost Price | J4: Selling Price | K4: Expected Profit | L4: Quantity | M4: Cartons | N4: Pieces/Carton | O4: Total Cost | P4: Barcode | Q4: Notes
A5: Al-Nour Shoes Factory | B5: Al-Nour Factory | C5: Casual | D5: Men | E5: Sneaker | F5: Model AN-101 | G5: Black | H5: 40-45 | I5: 250 | J5: 420 | K5: =IF(J5="","",J5-I5) | L5: 120 | M5: 10 | N5: 12 | O5: =IF(L5="","",I5*L5) | P5: 6221000000015 | Q5: Example row - overwrite with real data
K6: =IF(J6="","",J6-I6) | O6: =IF(L6="","",I6*L6)
K7: =IF(J7="","",J7-I7) | O7: =IF(L7="","",I7*L7)
K8: =IF(J8="","",J8-I8) | O8: =IF(L8="","",I8*L8)
K9: =IF(J9="","",J9-I9) | O9: =IF(L9="","",I9*L9)
K10: =IF(J10="","",J10-I10) | O10: =IF(L10="","",I10*L10)
K11: =IF(J11="","",J11-I11) | O11: =IF(L11="","",I11*L11)
K12: =IF(J12="","",J12-I12) | O12: =IF(L12="","",I12*L12)
K13: =IF(J13="","",J13-I13) | O13: =IF(L13="","",I13*L13)
K14: =IF(J14="","",J14-I14) | O14: =IF(L14="","",I14*L14)
K15: =IF(J15="","",J15-I15) | O15: =IF(L15="","",I15*L15)
K16: =IF(J16="","",J16-I16) | O16: =IF(L16="","",I16*L16)
K17: =IF(J17="","",J17-I17) | O17: =IF(L17="","",I17*L17)
... K54: =IF(J54="","",J54-I54) | O54: =IF(L54="","",I54*L54)
H56: TOTAL INVENTORY INVESTMENT | O56: =SUM(O5:O54)
A58: Legend: Yellow cells are editable inputs. Expected Profit and Total Cost calculate automatically. Row 5 is a sample entry — replace or extend the list below it.

Sheet Suppliers
A1: SUPPLIER DATABASE
A2: Approved / candidate suppliers directory
A4: Supplier Name | B4: Factory | C4: Address | D4: Phone | E4: WhatsApp | F4: Facebook | G4: Minimum Order | H4: Payment Terms | I4: Delivery Time | J4: Quality Rating (1-5) | K4: Personal Notes
A5: Al-Nour Shoes Factory | B5: Al-Nour Factory | C5: 10th of Ramadan City, Egypt | D5: 010xxxxxxxx | E5: 010xxxxxxxx | F5: facebook.com/alnourshoes | G5: 20 cartons | H5: 50% deposit / 50% on delivery | I5: 7-10 days | J5: 4 | K5: Example row - reliable, good quality control
A36: Legend: Yellow cells are editable inputs. Quality Rating uses a 1 (poor) to 5 (excellent) scale with automatic color scale formatting.

Sheet Sales Forecast
A1: SALES FORECAST
A2: Three scenarios: Conservative / Expected / Optimistic
A4: Metric | B4: Conservative | C4: Expected | D4: Optimistic
A5: Daily Units Sold (input) | B5: 8 | C5: 14 | D5: 22
A6: Average Selling Price (EGP) (input) | B6: 380 | C6: 420 | D6: 460
A7: Average Cost Price (EGP) (input) | B7: 230 | C7: 230 | D7: 230
A8: Weekly Sales (units) | B8: =B5*7 | C8: =C5*7 | D8: =D5*7
A9: Monthly Sales (units) | B9: =B5*30 | C9: =C5*30 | D9: =D5*30
A10: Monthly Revenue (EGP) | B10: =B9*B6 | C10: =C9*C6 | D10: =D9*D6
A11: Monthly COGS (EGP) | B11: =B9*B7 | C11: =C9*C7 | D11: =D9*D7
A12: Monthly Gross Profit (EGP) | B12: =B10-B11 | C12: =C10-C11 | D12: =D10-D11
A13: Gross Margin % | B13: =IF(B10=0,0,B12/B10) | C13: =IF(C10=0,0,C12/C10) | D13: =IF(D10=0,0,D12/D10)
A15: Legend: Yellow cells are editable inputs (daily units, avg. selling price, avg. cost price per scenario). All other figures calculate automatically. Expected scenario drives the Break-Even, Cash Flow, P&L and Final Summary sheets.

Sheet Break-Even
A1: BREAK-EVEN ANALYSIS
A2: Based on Expected scenario margins & monthly fixed costs
A4: Metric | B4: Value
A5: Fixed Monthly Costs (EGP) | B5: ='Monthly Expenses'!C19
A6: Average Selling Price (EGP) | B6: ='Sales Forecast'!C6
A7: Average Cost Price (EGP) | B7: ='Sales Forecast'!C7
A8: Contribution Margin per Unit (EGP) | B8: =B6-B7
A9: Monthly Break-Even Sales (units) | B9: =IF(B8=0,0,B5/B8)
A10: Daily Break-Even Units | B10: =B9/30
A11: Required Break-Even Revenue (EGP) | B11: =B9*B6
A12: Expected Monthly Unit Sales (units) | B12: ='Sales Forecast'!C9
A13: Expected Monthly Revenue (EGP) | B13: ='Sales Forecast'!C10
A14: Profit / (Loss) After Break-Even (EGP) | B14: =B13-(B12*B7)-B5
A16: Contribution Margin = Avg. Selling Price − Avg. Cost Price. Break-Even Units = Fixed Costs ÷ Contribution Margin. All values calculate automatically from the Monthly Expenses and Sales Forecast (Expected scenario) sheets.

Sheet Cash Flow
A1: CASH FLOW FORECAST
A2: 12-month projection (EGP) — Expected scenario
A4: Line Item | B4: Month 1 | C4: Month 2 | D4: Month 3 | E4: Month 4 | F4: Month 5 | G4: Month 6 | H4: Month 7 | I4: Month 8 | J4: Month 9 | K4: Month 10 | L4: Month 11 | M4: Month 12 | N4: Year Total
A5: Opening Cash | B5: =('Startup Costs'!C35)+('Inventory Plan'!O56) | C5: =B10 | D5: =C10 | E5: =D10 | F5: =E10 | G5: =F10 | H5: =G10 | I5: =H10 | J5: =I10 | ... M5: =L10 | N5: =B5
A6: Sales (Revenue) | B6: ='Sales Forecast'!C10 | C6: ='Sales Forecast'!C10 | D6: ='Sales Forecast'!C10 | E6: ='Sales Forecast'!C10 | F6: ='Sales Forecast'!C10 | G6: ='Sales Forecast'!C10 | H6: ='Sales Forecast'!C10 | I6: ='Sales Forecast'!C10 | J6: ='Sales Forecast'!C10 | K6: ='Sales Forecast'!C10 | L6: ='Sales Forecast'!C10 | M6: ='Sales Forecast'!C10 | N6: =SUM(B6:M6)
A7: Operating Expenses | B7: ='Monthly Expenses'!C19 | C7: ='Monthly Expenses'!C19 | D7: ='Monthly Expenses'!C19 | E7: ='Monthly Expenses'!C19 | F7: ='Monthly Expenses'!C19 | G7: ='Monthly Expenses'!C19 | H7: ='Monthly Expenses'!C19 | I7: ='Monthly Expenses'!C19 | J7: ='Monthly Expenses'!C19 | K7: ='Monthly Expenses'!C19 | L7: ='Monthly Expenses'!C19 | M7: ='Monthly Expenses'!C19 | N7: =SUM(B7:M7)
A8: Inventory Purchases | B8: ='Inventory Plan'!O56 | C8: 0 | D8: 0 | E8: 0 | F8: 0 | G8: 0 | H8: 0 | I8: 0 | J8: 0 | K8: 0 | L8: 0 | M8: 0 | N8: =SUM(B8:M8)
A9: Net Cash Flow | B9: =B6-B7-B8 | C9: =C6-C7-C8 | D9: =D6-D7-D8 | E9: =E6-E7-E8 | F9: =F6-F7-F8 | G9: =G6-G7-G8 | H9: =H6-H7-H8 | I9: =I6-I7-I8 | ... M9: =M6-M7-M8 | N9: =SUM(B9:M9)
A10: Closing Cash | B10: =B5+B9 | C10: =C5+C9 | D10: =D5+D9 | E10: =E5+E9 | F10: =F5+F9 | G10: =G5+G9 | H10: =H5+H9 | I10: =I5+I9 | ... M10: =M5+M9 | N10: =M10
A12: Opening Cash (Month 1) = Total Startup Cost + Total Inventory Investment (i.e. the capital you need on hand at launch). Sales and Expenses link automatically to the Sales Forecast (Expected) and Monthly Expenses sheets. Month 1 Inventory Purchases links to the Inventory Plan total; edit later months (white cells) if you plan restocking.

Sheet P&L
A1: PROFIT & LOSS STATEMENT
A2: Monthly & yearly — Expected scenario (EGP)
A4: Line Item | B4: Month 1 | C4: Month 2 | D4: Month 3 | E4: Month 4 | F4: Month 5 | G4: Month 6 | H4: Month 7 | I4: Month 8 | J4: Month 9 | K4: Month 10 | L4: Month 11 | M4: Month 12 | N4: Year Total
A5: Revenue | B5: ='Sales Forecast'!C10 | C5: ='Sales Forecast'!C10 | D5: ='Sales Forecast'!C10 | E5: ='Sales Forecast'!C10 | F5: ='Sales Forecast'!C10 | G5: ='Sales Forecast'!C10 | H5: ='Sales Forecast'!C10 | I5: ='Sales Forecast'!C10 | J5: ='Sales Forecast'!C10 | K5: ='Sales Forecast'!C10 | L5: ='Sales Forecast'!C10 | M5: ='Sales Forecast'!C10 | N5: =SUM(B5:M5)
A6: COGS | B6: ='Sales Forecast'!C11 | C6: ='Sales Forecast'!C11 | D6: ='Sales Forecast'!C11 | E6: ='Sales Forecast'!C11 | F6: ='Sales Forecast'!C11 | G6: ='Sales Forecast'!C11 | H6: ='Sales Forecast'!C11 | I6: ='Sales Forecast'!C11 | J6: ='Sales Forecast'!C11 | K6: ='Sales Forecast'!C11 | L6: ='Sales Forecast'!C11 | M6: ='Sales Forecast'!C11 | N6: =SUM(B6:M6)
A7: Gross Profit | B7: =B5-B6 | C7: =C5-C6 | D7: =D5-D6 | E7: =E5-E6 | F7: =F5-F6 | G7: =G5-G6 | H7: =H5-H6 | I7: =I5-I6 | ... M7: =M5-M6 | N7: =SUM(B7:M7)
A8: Operating Expenses | B8: ='Monthly Expenses'!C19 | C8: ='Monthly Expenses'!C19 | D8: ='Monthly Expenses'!C19 | E8: ='Monthly Expenses'!C19 | F8: ='Monthly Expenses'!C19 | G8: ='Monthly Expenses'!C19 | H8: ='Monthly Expenses'!C19 | I8: ='Monthly Expenses'!C19 | J8: ='Monthly Expenses'!C19 | K8: ='Monthly Expenses'!C19 | L8: ='Monthly Expenses'!C19 | M8: ='Monthly Expenses'!C19 | N8: =SUM(B8:M8)
A9: Net Profit | B9: =B7-B8 | C9: =C7-C8 | D9: =D7-D8 | E9: =E7-E8 | F9: =F7-F8 | G9: =G7-G8 | H9: =H7-H8 | I9: =I7-I8 | ... M9: =M7-M8 | N9: =SUM(B9:M9)
A11: Revenue and COGS link to the Sales Forecast (Expected scenario); Operating Expenses link to the Monthly Expenses sheet. Update those sheets to flow changes through automatically.

Sheet Inventory Tracker
A1: INVENTORY TRACKER
A2: Live stock levels & movement classification
A4: Model Name | B4: Category | C4: Current Stock | D4: Sold Qty | E4: Remaining Stock | F4: Cost Price | G4: Sale Price | H4: Movement Status | I4: Notes
A5: Model AN-101 (example) | B5: Casual | C5: 120 | D5: 45 | E5: =IF(C5="","",C5-D5) | F5: 250 | G5: 420 | H5: =IF(C5="","",IF(D5>=C5*0.7,"Fast Moving",IF(D5<=C5*0.1,"Dead Stock","Slow Moving"))) | I5: Example row - overwrite with real data
E6: =IF(C6="","",C6-D6) | H6: =IF(C6="","",IF(D6>=C6*0.7,"Fast Moving",IF(D6<=C6*0.1,"Dead Stock","Slow Moving")))
E7: =IF(C7="","",C7-D7) | H7: =IF(C7="","",IF(D7>=C7*0.7,"Fast Moving",IF(D7<=C7*0.1,"Dead Stock","Slow Moving")))
E8: =IF(C8="","",C8-D8) | H8: =IF(C8="","",IF(D8>=C8*0.7,"Fast Moving",IF(D8<=C8*0.1,"Dead Stock","Slow Moving")))
E9: =IF(C9="","",C9-D9) | H9: =IF(C9="","",IF(D9>=C9*0.7,"Fast Moving",IF(D9<=C9*0.1,"Dead Stock","Slow Moving")))
E10: =IF(C10="","",C10-D10) | H10: =IF(C10="","",IF(D10>=C10*0.7,"Fast Moving",IF(D10<=C10*0.1,"Dead Stock","Slow Moving")))
E11: =IF(C11="","",C11-D11) | H11: =IF(C11="","",IF(D11>=C11*0.7,"Fast Moving",IF(D11<=C11*0.1,"Dead Stock","Slow Moving")))
E12: =IF(C12="","",C12-D12) | H12: =IF(C12="","",IF(D12>=C12*0.7,"Fast Moving",IF(D12<=C12*0.1,"Dead Stock","Slow Moving")))
E13: =IF(C13="","",C13-D13) | H13: =IF(C13="","",IF(D13>=C13*0.7,"Fast Moving",IF(D13<=C13*0.1,"Dead Stock","Slow Moving")))
E14: =IF(C14="","",C14-D14) | H14: =IF(C14="","",IF(D14>=C14*0.7,"Fast Moving",IF(D14<=C14*0.1,"Dead Stock","Slow Moving")))
E15: =IF(C15="","",C15-D15) | H15: =IF(C15="","",IF(D15>=C15*0.7,"Fast Moving",IF(D15<=C15*0.1,"Dead Stock","Slow Moving")))
E16: =IF(C16="","",C16-D16) | H16: =IF(C16="","",IF(D16>=C16*0.7,"Fast Moving",IF(D16<=C16*0.1,"Dead Stock","Slow Moving")))
E17: =IF(C17="","",C17-D17) | H17: =IF(C17="","",IF(D17>=C17*0.7,"Fast Moving",IF(D17<=C17*0.1,"Dead Stock","Slow Moving")))
... E44: =IF(C44="","",C44-D44) | H44: =IF(C44="","",IF(D44>=C44*0.7,"Fast Moving",IF(D44<=C44*0.1,"Dead Stock","Slow Moving")))
B46: TOTAL REMAINING INVENTORY VALUE (EGP) | E46: =SUMPRODUCT(E5:E44,F5:F44)
A48: Movement Status: Fast Moving = sold ≥70% of stock, Dead Stock = sold ≤10% of stock, otherwise Slow Moving. Thresholds can be adjusted in the formula.

Sheet Product Dashboard
A1: PRODUCT PERFORMANCE DASHBOARD
A2: Top / worst sellers and margin leaders (auto-ranked from Inventory Tracker)
B4: TOP 5 SELLING PRODUCTS (by units sold) | G4: BOTTOM 5 SELLING PRODUCTS
B5: Rank | C5: Product | D5: Units Sold | G5: Product | H5: Units Sold | M5: ='Inventory Tracker'!G5-'Inventory Tracker'!F5
B6: 1 | C6: =IFERROR(INDEX('Inventory Tracker'!$A$5:$A$44,MATCH(D6,'Inventory Tracker'!$D$5:$D$44,0)),"-") | D6: =IFERROR(LARGE('Inventory Tracker'!$D$5:$D$44,1),0) | G6: =IFERROR(INDEX('Inventory Tracker'!$A$5:$A$44,MATCH(H6,'Inventory Tracker'!$D$5:$D$44,0)),"-") | H6: =IFERROR(SMALL('Inventory Tracker'!$D$5:$D$44,1),0) | M6: ='Inventory Tracker'!G6-'Inventory Tracker'!F6
B7: 2 | C7: =IFERROR(INDEX('Inventory Tracker'!$A$5:$A$44,MATCH(D7,'Inventory Tracker'!$D$5:$D$44,0)),"-") | D7: =IFERROR(LARGE('Inventory Tracker'!$D$5:$D$44,2),0) | G7: =IFERROR(INDEX('Inventory Tracker'!$A$5:$A$44,MATCH(H7,'Inventory Tracker'!$D$5:$D$44,0)),"-") | H7: =IFERROR(SMALL('Inventory Tracker'!$D$5:$D$44,2),0) | M7: ='Inventory Tracker'!G7-'Inventory Tracker'!F7
B8: 3 | C8: =IFERROR(INDEX('Inventory Tracker'!$A$5:$A$44,MATCH(D8,'Inventory Tracker'!$D$5:$D$44,0)),"-") | D8: =IFERROR(LARGE('Inventory Tracker'!$D$5:$D$44,3),0) | G8: =IFERROR(INDEX('Inventory Tracker'!$A$5:$A$44,MATCH(H8,'Inventory Tracker'!$D$5:$D$44,0)),"-") | H8: =IFERROR(SMALL('Inventory Tracker'!$D$5:$D$44,3),0) | M8: ='Inventory Tracker'!G8-'Inventory Tracker'!F8
B9: 4 | C9: =IFERROR(INDEX('Inventory Tracker'!$A$5:$A$44,MATCH(D9,'Inventory Tracker'!$D$5:$D$44,0)),"-") | D9: =IFERROR(LARGE('Inventory Tracker'!$D$5:$D$44,4),0) | G9: =IFERROR(INDEX('Inventory Tracker'!$A$5:$A$44,MATCH(H9,'Inventory Tracker'!$D$5:$D$44,0)),"-") | H9: =IFERROR(SMALL('Inventory Tracker'!$D$5:$D$44,4),0) | M9: ='Inventory Tracker'!G9-'Inventory Tracker'!F9
B10: 5 | C10: =IFERROR(INDEX('Inventory Tracker'!$A$5:$A$44,MATCH(D10,'Inventory Tracker'!$D$5:$D$44,0)),"-") | D10: =IFERROR(LARGE('Inventory Tracker'!$D$5:$D$44,5),0) | G10: =IFERROR(INDEX('Inventory Tracker'!$A$5:$A$44,MATCH(H10,'Inventory Tracker'!$D$5:$D$44,0)),"-") | H10: =IFERROR(SMALL('Inventory Tracker'!$D$5:$D$44,5),0) | M10: ='Inventory Tracker'!G10-'Inventory Tracker'!F10
M11: ='Inventory Tracker'!G11-'Inventory Tracker'!F11
M12: ='Inventory Tracker'!G12-'Inventory Tracker'!F12
B13: MARGIN LEADERS (by EGP margin per unit) | M13: ='Inventory Tracker'!G13-'Inventory Tracker'!F13
B14: Rank | C14: Product | D14: Margin/Unit | M14: ='Inventory Tracker'!G14-'Inventory Tracker'!F14
B15: 1 | C15: =IFERROR(INDEX('Inventory Tracker'!$A$5:$A$44,MATCH(D15,$M$5:$M$44,0)),"-") | D15: =IFERROR(LARGE($M$5:$M$44,1),0) | M15: ='Inventory Tracker'!G15-'Inventory Tracker'!F15
B16: 2 | C16: =IFERROR(INDEX('Inventory Tracker'!$A$5:$A$44,MATCH(D16,$M$5:$M$44,0)),"-") | D16: =IFERROR(LARGE($M$5:$M$44,2),0) | M16: ='Inventory Tracker'!G16-'Inventory Tracker'!F16
B17: 3 | C17: =IFERROR(INDEX('Inventory Tracker'!$A$5:$A$44,MATCH(D17,$M$5:$M$44,0)),"-") | D17: =IFERROR(LARGE($M$5:$M$44,3),0) | M17: ='Inventory Tracker'!G17-'Inventory Tracker'!F17
B18: 4 | C18: =IFERROR(INDEX('Inventory Tracker'!$A$5:$A$44,MATCH(D18,$M$5:$M$44,0)),"-") | D18: =IFERROR(LARGE($M$5:$M$44,4),0) | M18: ='Inventory Tracker'!G18-'Inventory Tracker'!F18
B19: 5 | C19: =IFERROR(INDEX('Inventory Tracker'!$A$5:$A$44,MATCH(D19,$M$5:$M$44,0)),"-") | D19: =IFERROR(LARGE($M$5:$M$44,5),0) | M19: ='Inventory Tracker'!G19-'Inventory Tracker'!F19
M20: ='Inventory Tracker'!G20-'Inventory Tracker'!F20
B21: Rankings pull live from the Inventory Tracker sheet (units sold and cost/sale prices). Add products there and this dashboard updates automatically. A hidden helper column (M) computes per-unit margin. | M21: ='Inventory Tracker'!G21-'Inventory Tracker'!F21
M22: ='Inventory Tracker'!G22-'Inventory Tracker'!F22
M23: ='Inventory Tracker'!G23-'Inventory Tracker'!F23
M24: ='Inventory Tracker'!G24-'Inventory Tracker'!F24
M25: ='Inventory Tracker'!G25-'Inventory Tracker'!F25
M26: ='Inventory Tracker'!G26-'Inventory Tracker'!F26
M27: ='Inventory Tracker'!G27-'Inventory Tracker'!F27
M28: ='Inventory Tracker'!G28-'Inventory Tracker'!F28
M29: ='Inventory Tracker'!G29-'Inventory Tracker'!F29
M30: ='Inventory Tracker'!G30-'Inventory Tracker'!F30
M31: ='Inventory Tracker'!G31-'Inventory Tracker'!F31
M32: ='Inventory Tracker'!G32-'Inventory Tracker'!F32
M33: ='Inventory Tracker'!G33-'Inventory Tracker'!F33
... M44: ='Inventory Tracker'!G44-'Inventory Tracker'!F44

Sheet Expense Tracker
A1: EXPENSE TRACKER
A2: Log every actual expense as it occurs
A4: Date | B4: Expense Category | C4: Amount (EGP) | D4: Payment Method | E4: Supplier | F4: Notes
A5: 46239 | B5: Rent | C5: 15000 | D5: Bank Transfer | E5: Landlord | F5: Example row
A66: SUMMARY BY CATEGORY
A67: Rent | B67: =SUMIF(B5:B64,A67,C5:C64)
A68: Salaries | B68: =SUMIF(B5:B64,A68,C5:C64)
A69: Electricity | B69: =SUMIF(B5:B64,A69,C5:C64)
A70: Water | B70: =SUMIF(B5:B64,A70,C5:C64)
A71: Internet | B71: =SUMIF(B5:B64,A71,C5:C64)
A72: Cleaning | B72: =SUMIF(B5:B64,A72,C5:C64)
A73: Packaging | B73: =SUMIF(B5:B64,A73,C5:C64)
A74: Transportation | B74: =SUMIF(B5:B64,A74,C5:C64)
A75: Maintenance | B75: =SUMIF(B5:B64,A75,C5:C64)
A76: Taxes | B76: =SUMIF(B5:B64,A76,C5:C64)
A77: Marketing | B77: =SUMIF(B5:B64,A77,C5:C64)
A78: Unexpected | B78: =SUMIF(B5:B64,A78,C5:C64)
A79: Other | B79: =SUMIF(B5:B64,A79,C5:C64)
A80: TOTAL LOGGED EXPENSES | B80: =SUM(B67:B79)
A82: Log actual expenses here as they happen. The category summary and total update automatically via SUMIF formulas.

Sheet Sales Tracker
A1: SALES TRACKER
A2: Daily transaction log with automatic summaries
A4: Date | B4: Invoice # | C4: Customer | D4: Product | E4: Category | F4: Size | G4: Selling Price | H4: Discount | I4: Net Price | J4: Payment Method | K4: Salesperson
A5: 46239 | B5: INV-0001 | C5: Walk-in Customer | D5: Model AN-101 | E5: Casual | F5: 42 | G5: 420 | H5: 0 | I5: =IF(G5="","",G5-H5) | J5: Cash | K5: Example row
I6: =IF(G6="","",G6-H6)
I7: =IF(G7="","",G7-H7)
I8: =IF(G8="","",G8-H8)
I9: =IF(G9="","",G9-H9)
I10: =IF(G10="","",G10-H10)
I11: =IF(G11="","",G11-H11)
I12: =IF(G12="","",G12-H12)
I13: =IF(G13="","",G13-H13)
I14: =IF(G14="","",G14-H14)
I15: =IF(G15="","",G15-H15)
I16: =IF(G16="","",G16-H16)
I17: =IF(G17="","",G17-H17)
... I84: =IF(G84="","",G84-H84)
A86: DAILY / MONTHLY SUMMARY
A87: Total Transactions | B87: =COUNT(I5:I84)
A88: Total Net Sales (EGP) | B88: =SUM(I5:I84)
A89: Average Sale Value (EGP) | B89: =IFERROR(B88/B87,0)
A90: Today's Sales (EGP) | B90: =SUMIF(A5:A84,TODAY(),I5:I84)
A91: This Month's Sales (EGP) | B91: =SUMPRODUCT((TEXT(A5:A84,"yyyymm")=TEXT(TODAY(),"yyyymm"))*N(I5:I84))
A93: Log every actual sale here. Net Price, and the summary metrics below, calculate automatically.

Sheet KPI Dashboard
A1: KPI DASHBOARD
A2: Key performance indicators at a glance
A4: Expected Monthly Revenue | D4: Current Inventory Value | G4: Average Gross Margin %
A5: Expected Gross Profit | D5: Monthly Operating Expenses | G5: Break-Even Units / Month
A6: Expected Net Profit (Month 1) | D6: Closing Cash (Month 12) | G6: Actual Sales-to-Date (Tracker)
A7: ='P&L'!B9 | D7: ='Cash Flow'!M10 | G7: ='Sales Tracker'!B88
A10: MONTHLY TREND (from P&L sheet)
A32: EXPENSE BREAKDOWN
A52: All KPI tiles and charts update automatically as you fill in the Business, Costs, Sales Forecast and Tracker sheets.

Sheet Market Research
A1: MARKET RESEARCH
A2: Competitor landscape in El Warraq & surrounding areas
A4: Competitor Name | B4: Location | C4: Store Size (sqm) | D4: Strengths | E4: Weaknesses | F4: Price Range | G4: Best Selling Products | H4: Brands Carried | I4: Target Customers | J4: Notes
A5: Example Competitor Store | B5: El Warraq Main St. | C5: 45 | D5: Prime location, low prices | E5: Limited sizes, poor lighting | F5: 150-350 EGP | G5: School shoes | H5: Local brands | I5: Budget families | J5: Example row - overwrite with real research
A18: Visit or research nearby competitors and complete one row per store. This informs pricing and positioning decisions in the SWOT and Marketing Plan sheets.

Sheet Risk Analysis
A1: RISK ANALYSIS
A2: Identify, score and mitigate key business risks
A4: Possible Risk | B4: Likelihood | C4: Impact | D4: Risk Score | E4: Mitigation Plan
A5: Low footfall / weak location visibility | B5: Medium | C5: Medium | D5: =(IF(B5="Low",1,IF(B5="Medium",2,IF(B5="High",3,0))))*(IF(C5="Low",1,IF(C5="Medium",2,IF(C5="High",3,0))))
A6: Strong price competition from nearby stores | B6: Medium | C6: Medium | D6: =(IF(B6="Low",1,IF(B6="Medium",2,IF(B6="High",3,0))))*(IF(C6="Low",1,IF(C6="Medium",2,IF(C6="High",3,0))))
A7: Slow-moving / dead stock (wrong sizes or styles) | B7: Medium | C7: Medium | D7: =(IF(B7="Low",1,IF(B7="Medium",2,IF(B7="High",3,0))))*(IF(C7="Low",1,IF(C7="Medium",2,IF(C7="High",3,0))))
A8: Supplier delivery delays | B8: Medium | C8: Medium | D8: =(IF(B8="Low",1,IF(B8="Medium",2,IF(B8="High",3,0))))*(IF(C8="Low",1,IF(C8="Medium",2,IF(C8="High",3,0))))
A9: Currency devaluation raising import/leather costs | B9: Medium | C9: Medium | D9: =(IF(B9="Low",1,IF(B9="Medium",2,IF(B9="High",3,0))))*(IF(C9="Low",1,IF(C9="Medium",2,IF(C9="High",3,0))))
A10: Seasonality (low demand off-season) | B10: Medium | C10: Medium | D10: =(IF(B10="Low",1,IF(B10="Medium",2,IF(B10="High",3,0))))*(IF(C10="Low",1,IF(C10="Medium",2,IF(C10="High",3,0))))
A11: Staff turnover / theft | B11: Medium | C11: Medium | D11: =(IF(B11="Low",1,IF(B11="Medium",2,IF(B11="High",3,0))))*(IF(C11="Low",1,IF(C11="Medium",2,IF(C11="High",3,0))))
A12: Rent increase at lease renewal | B12: Medium | C12: Medium | D12: =(IF(B12="Low",1,IF(B12="Medium",2,IF(B12="High",3,0))))*(IF(C12="Low",1,IF(C12="Medium",2,IF(C12="High",3,0))))
A13: Economic downturn reducing disposable income | B13: Medium | C13: Medium | D13: =(IF(B13="Low",1,IF(B13="Medium",2,IF(B13="High",3,0))))*(IF(C13="Low",1,IF(C13="Medium",2,IF(C13="High",3,0))))
A14: Online / e-commerce competition | B14: Medium | C14: Medium | D14: =(IF(B14="Low",1,IF(B14="Medium",2,IF(B14="High",3,0))))*(IF(C14="Low",1,IF(C14="Medium",2,IF(C14="High",3,0))))
A16: Risk Score = Likelihood x Impact (1-3 scale each). Scores 6-9 = high priority (red), 3-4 = medium (yellow), 1-2 = low (green). Fill in the Mitigation Plan for every medium/high risk.

Sheet Marketing Plan
A1: MARKETING PLAN
A2: Offline & online marketing channel budget and plan
A4: Channel | B4: Active? (Y/N) | C4: Monthly Budget (EGP) | D4: Frequency / Plan | E4: Notes
A5: Offline Marketing (general) | B5: Y
A6: Facebook | B6: Y
A7: Instagram | B7: Y
A8: TikTok | B8: Y
A9: Google Maps Listing | B9: Y
A10: Flyers | B10: Y
A11: Street Banners | B11: Y
A12: Referral Campaigns | B12: Y
A13: Seasonal Offers / Promotions | B13: Y
A15: TOTAL MARKETING BUDGET / MONTH | C15: =SUMIF(B5:B13,"Y",C5:C13)
A17: Mark each channel Active (Y/N); the total budget only sums channels marked Y. This should reconcile with the 'Marketing' line in Monthly Expenses.

Sheet SWOT
A1: SWOT ANALYSIS
A2: Strengths, Weaknesses, Opportunities, Threats
B4: STRENGTHS | D4: WEAKNESSES
B5: e.g. Prime location with high foot traffic | D5: e.g. Limited initial capital
B14: OPPORTUNITIES | D14: THREATS
B15: e.g. Growing residential population in El Warraq | D15: e.g. New competitor entry / economic slowdown
B24: Fill in each yellow cell with one point per line. Use the Market Research and Risk Analysis sheets as input.

Sheet Action Plan
A1: ACTION PLAN
A2: Pre-opening task list and ownership
A4: Task | B4: Responsible | C4: Budget (EGP) | D4: Priority | E4: Deadline | F4: Status
A5: Finalize lease agreement | D5: Medium | F5: Not Started
A6: Complete commercial registration | D6: Medium | F6: Not Started
A7: Complete tax registration | D7: Medium | F7: Not Started
A8: Renovation & interior fit-out | D8: Medium | F8: Not Started
A9: Order signboard & branding | D9: Medium | F9: Not Started
A10: Purchase POS system & cameras | D10: Medium | F10: Not Started
A11: Place first inventory order | D11: Medium | F11: Not Started
A12: Hire & train staff | D12: Medium | F12: Not Started
A13: Set up social media pages | D13: Medium | F13: Not Started
A14: Launch marketing campaign | D14: Medium | F14: Not Started
A15: Soft opening | D15: Medium | F15: Not Started
A16: Grand opening event | D16: Medium | F16: Not Started
A18: TOTAL ACTION PLAN BUDGET | C18: =SUM(C5:C16)
A20: Update Status as tasks progress; conditional formatting highlights Done (green), In Progress (yellow) and Delayed (red).

Sheet Final Summary
A1: FINAL SUMMARY
A2: Investor / bank-ready feasibility snapshot
A4: Metric | B4: Value | C4: Comments
A5: Total Startup Investment (EGP) | B5: =('Startup Costs'!C35)+('Inventory Plan'!O56) | C5: Startup Costs + Initial Inventory
A6: Working Capital Needed (3 months, EGP) | B6: =('Monthly Expenses'!C19)*3 | C6: 3x monthly operating expenses buffer
A7: Total Capital Required (EGP) | B7: =B5+B6 | C7: Startup Investment plus Working Capital
A8: Expected Monthly Revenue (EGP) | B8: ='Sales Forecast'!C10 | C8: Expected scenario, Sales Forecast sheet
A9: Expected Monthly Net Profit (EGP) | B9: ='P&L'!B9 | C9: From P&L sheet
A10: Expected Annual Net Profit (EGP) | B10: ='P&L'!N9 | C10: From P&L sheet, Year Total
A11: Return on Investment - Year 1 (%) | B11: =IFERROR(B10/B7,0) | C11: Annual Net Profit / Total Capital Required
A12: Monthly Break-Even Sales (units) | B12: ='Break-Even'!B9 | C12: From Break-Even sheet
A13: Estimated Break-Even Month | B13: =IF(B9<=0,"Not within 12 months",TEXT(ROUNDUP(B7/B9,0),"0")&" months of net profit to recover capital") | C13: First month projected profit covers investment
A14: Minimum Cash Needed at Launch (EGP) | B14: =B7 | C14: Equal to Total Capital Required
A16: AUTOMATED WARNINGS
A17: =IF(B9<0,"⚠ Warning: Expected monthly profit is NEGATIVE at current assumptions — revisit pricing, costs or expenses.","✓ Expected monthly profit is positive under current assumptions.")
A18: =IF('Cash Flow'!M10<0,"⚠ Warning: Projected cash balance goes NEGATIVE within 12 months — plan for extra working capital.","✓ Cash balance remains positive across the 12-month projection.")
A20: This summary consolidates every other sheet automatically. Update Business Info, Startup Costs, Monthly Expenses, Inventory Plan and Sales Forecast, and this page — and the KPI Dashboard — refresh instantly.
